# java虚拟机指令集对照表

指令码地址( https://docs.oracle.com/javase/specs/jvms/se8/html/jvms-6.html#jvms-6.4-mnemonic )

| 序号 | 指令 | Operation | Format | Forms |
| ----| ---- | ---- | ---- | ---- |
| 1| mnemonic | 指令的简单描述 | mnemonicoperand1operand2 | mnemonic = opcode |
| 2| aaload | Load reference from array | aaload | aaload = 50 (0x32) |
| 3| aastore | Store into reference array | aastore | aastore = 83 (0x53) |
| 4| aconst_null | Push null | aconst_null | aconst_null = 1 (0x1) |
| 5| aload | Load reference from local variable | aloadindex | aload = 25 (0x19) |
| 6| aload_<n> | Load reference from local variable | aload_<n> | aload_0 = 42 (0x2a)aload_1 = 43 (0x2b)aload_2 = 44 (0x2c)aload_3 = 45 (0x2d) |
| 7| anewarray | Create new array of reference | anewarrayindexbyte1indexbyte2 | anewarray = 189 (0xbd) |
| 8| areturn | Return reference from method | areturn | areturn = 176 (0xb0) |
| 9| arraylength | Get length of array | arraylength | arraylength = 190 (0xbe) |
| 10| astore | Store reference into local variable | astoreindex | astore = 58 (0x3a) |
| 11| astore_<n> | Store reference into local variable | astore_<n> | astore_0 = 75 (0x4b)astore_1 = 76 (0x4c)astore_2 = 77 (0x4d)astore_3 = 78 (0x4e) |
| 12| athrow | Throw exception or error | athrow | athrow = 191 (0xbf) |
| 13| baload | Load byte or boolean from array | baload | baload = 51 (0x33) |
| 14| bastore | Store into byte or boolean array | bastore | bastore = 84 (0x54) |
| 15| bipush | Push byte | bipushbyte | bipush = 16 (0x10) |
| 16| caload | Load char from array | caload | caload = 52 (0x34) |
| 17| castore | Store into char array | castore | castore = 85 (0x55) |
| 18| checkcast | Check whether object is of given type | checkcastindexbyte1indexbyte2 | checkcast = 192 (0xc0) |
| 19| d2f | Convert double to float | d2f | d2f = 144 (0x90) |
| 20| d2i | Convert double to int | d2i | d2i = 142 (0x8e) |
| 21| d2l | Convert double to long | d2l | d2l = 143 (0x8f) |
| 22| dadd | Add double | dadd | dadd = 99 (0x63) |
| 23| daload | Load double from array | daload | daload = 49 (0x31) |
| 24| dastore | Store into double array | dastore | dastore = 82 (0x52) |
| 25| dcmp<op> | Compare double | dcmp<op> | dcmpg = 152 (0x98)dcmpl = 151 (0x97) |
| 26| dconst_<d> | Push double | dconst_<d> | dconst_0 = 14 (0xe)dconst_1 = 15 (0xf) |
| 27| ddiv | Divide double | ddiv | ddiv = 111 (0x6f) |
| 28| dload | Load double from local variable | dloadindex | dload = 24 (0x18) |
| 29| dload_<n> | Load double from local variable | dload_<n> | dload_0 = 38 (0x26)dload_1 = 39 (0x27)dload_2 = 40 (0x28)dload_3 = 41 (0x29) |
| 30| dmul | Multiply double | dmul | dmul = 107 (0x6b) |
| 31| dneg | Negate double | dneg | dneg = 119 (0x77) |
| 32| drem | Remainder double | drem | drem = 115 (0x73) |
| 33| dreturn | Return double from method | dreturn | dreturn = 175 (0xaf) |
| 34| dstore | Store double into local variable | dstoreindex | dstore = 57 (0x39) |
| 35| dstore_<n> | Store double into local variable | dstore_<n> | dstore_0 = 71 (0x47)dstore_1 = 72 (0x48)dstore_2 = 73 (0x49)dstore_3 = 74 (0x4a) |
| 36| dsub | Subtract double | dsub | dsub = 103 (0x67) |
| 37| dup | Duplicate the top operand stack value | dup | dup = 89 (0x59) |
| 38| dup_x1 | Duplicate the top operand stack value and insert two values down | dup_x1 | dup_x1 = 90 (0x5a) |
| 39| dup_x2 | Duplicate the top operand stack value and insert two or three values down | dup_x2 | dup_x2 = 91 (0x5b) |
| 40| dup2 | Duplicate the top one or two operand stack values | dup2 | dup2 = 92 (0x5c) |
| 41| dup2_x1 | Duplicate the top one or two operand stack values and insert two or three values down | dup2_x1 | dup2_x1 = 93 (0x5d) |
| 42| dup2_x2 | Duplicate the top one or two operand stack values and insert two, three, or four values down | dup2_x2 | dup2_x2 = 94 (0x5e) |
| 43| f2d | Convert float to double | f2d | f2d = 141 (0x8d) |
| 44| f2i | Convert float to int | f2i | f2i = 139 (0x8b) |
| 45| f2l | Convert float to long | f2l | f2l = 140 (0x8c) |
| 46| fadd | Add float | fadd | fadd = 98 (0x62) |
| 47| faload | Load float from array | faload | faload = 48 (0x30) |
| 48| fastore | Store into float array | fastore | fastore = 81 (0x51) |
| 49| fcmp<op> | Compare float | fcmp<op> | fcmpg = 150 (0x96)fcmpl = 149 (0x95) |
| 50| fconst_<f> | Push float | fconst_<f> | fconst_0 = 11 (0xb)fconst_1 = 12 (0xc)fconst_2 = 13 (0xd) |
| 51| fdiv | Divide float | fdiv | fdiv = 110 (0x6e) |
| 52| fload | Load float from local variable | floadindex | fload = 23 (0x17) |
| 53| fload_<n> | Load float from local variable | fload_<n> | fload_0 = 34 (0x22)fload_1 = 35 (0x23)fload_2 = 36 (0x24)fload_3 = 37 (0x25) |
| 54| fmul | Multiply float | fmul | fmul = 106 (0x6a) |
| 55| fneg | Negate float | fneg | fneg = 118 (0x76) |
| 56| frem | Remainder float | frem | frem = 114 (0x72) |
| 57| freturn | Return float from method | freturn | freturn = 174 (0xae) |
| 58| fstore | Store float into local variable | fstoreindex | fstore = 56 (0x38) |
| 59| fstore_<n> | Store float into local variable | fstore_<n> | fstore_0 = 67 (0x43)fstore_1 = 68 (0x44)fstore_2 = 69 (0x45)fstore_3 = 70 (0x46) |
| 60| fsub | Subtract float | fsub | fsub = 102 (0x66) |
| 61| getfield | Fetch field from object | getfieldindexbyte1indexbyte2 | getfield = 180 (0xb4) |
| 62| getstatic | Get static field from class | getstaticindexbyte1indexbyte2 | getstatic = 178 (0xb2) |
| 63| goto | Branch always | gotobranchbyte1branchbyte2 | goto = 167 (0xa7) |
| 64| goto_w | Branch always (wide index) | goto_wbranchbyte1branchbyte2branchbyte3branchbyte4 | goto_w = 200 (0xc8) |
| 65| i2b | Convert int to byte | i2b | i2b = 145 (0x91) |
| 66| i2c | Convert int to char | i2c | i2c = 146 (0x92) |
| 67| i2d | Convert int to double | i2d | i2d = 135 (0x87) |
| 68| i2f | Convert int to float | i2f | i2f = 134 (0x86) |
| 69| i2l | Convert int to long | i2l | i2l = 133 (0x85) |
| 70| i2s | Convert int to short | i2s | i2s = 147 (0x93) |
| 71| iadd | Add int | iadd | iadd = 96 (0x60) |
| 72| iaload | Load int from array | iaload | iaload = 46 (0x2e) |
| 73| iand | Boolean AND int | iand | iand = 126 (0x7e) |
| 74| iastore | Store into int array | iastore | iastore = 79 (0x4f) |
| 75| iconst_<i> | Push int constant | iconst_<i> | iconst_m1 = 2 (0x2) iconst_0 = 3 (0x3) iconst_1 = 4 (0x4) iconst_2 = 5 (0x5) iconst_3 = 6 (0x6) iconst_4 = 7 (0x7) iconst_5 = 8 (0x8) |
| 76| idiv | Divide int | idiv | idiv = 108 (0x6c) |
| 77| if_acmp<cond> | Branch if reference comparison succeeds | if_acmp<cond>branchbyte1branchbyte2 | if_acmpeq = 165 (0xa5)if_acmpne = 166 (0xa6) |
| 78| if_icmp<cond> | Branch if int comparison succeeds | if_icmp<cond>branchbyte1branchbyte2 | if_icmpeq = 159 (0x9f)if_icmpne = 160 (0xa0)if_icmplt = 161 (0xa1)if_icmpge = 162 (0xa2)if_icmpgt = 163 (0xa3)if_icmple = 164 (0xa4) |
| 79| if<cond> | Branch if int comparison with zero succeeds | if<cond>branchbyte1branchbyte2 | ifeq = 153 (0x99)ifne = 154 (0x9a)iflt = 155 (0x9b)ifge = 156 (0x9c)ifgt = 157 (0x9d)ifle = 158 (0x9e) |
| 80| ifnonnull | Branch if reference not null | ifnonnullbranchbyte1branchbyte2 | ifnonnull = 199 (0xc7) |
| 81| ifnull | Branch if reference is null | ifnullbranchbyte1branchbyte2 | ifnull = 198 (0xc6) |
| 82| iinc | Increment local variable by constant | iincindexconst | iinc = 132 (0x84) |
| 83| iload | Load int from local variable | iloadindex | iload = 21 (0x15) |
| 84| iload_<n> | Load int from local variable | iload_<n> | iload_0 = 26 (0x1a)iload_1 = 27 (0x1b)iload_2 = 28 (0x1c)iload_3 = 29 (0x1d) |
| 85| imul | Multiply int | imul | imul = 104 (0x68) |
| 86| ineg | Negate int | ineg | ineg = 116 (0x74) |
| 87| instanceof | Determine if object is of given type | instanceofindexbyte1indexbyte2 | instanceof = 193 (0xc1) |
| 88| invokedynamic | Invoke dynamic method | invokedynamicindexbyte1indexbyte200 | invokedynamic = 186 (0xba) |
| 89| invokeinterface | Invoke interface method | invokeinterfaceindexbyte1indexbyte2count0 | invokeinterface = 185 (0xb9) |
| 90| invokespecial | Invoke instance method; special handling for superclass, private, and instance initialization method invocations | invokespecialindexbyte1indexbyte2 | invokespecial = 183 (0xb7) |
| 91| invokestatic | Invoke a class (static) method | invokestaticindexbyte1indexbyte2 | invokestatic = 184 (0xb8) |
| 92| invokevirtual | Invoke instance method; dispatch based on class | invokevirtualindexbyte1indexbyte2 | invokevirtual = 182 (0xb6) |
| 93| ior | Boolean OR int | ior | ior = 128 (0x80) |
| 94| irem | Remainder int | irem | irem = 112 (0x70) |
| 95| ireturn | Return int from method | ireturn | ireturn = 172 (0xac) |
| 96| ishl | Shift left int | ishl | ishl = 120 (0x78) |
| 97| ishr | Arithmetic shift right int | ishr | ishr = 122 (0x7a) |
| 98| istore | Store int into local variable | istoreindex | istore = 54 (0x36) |
| 99| istore_<n> | Store int into local variable | istore_<n> | istore_0 = 59 (0x3b)istore_1 = 60 (0x3c)istore_2 = 61 (0x3d)istore_3 = 62 (0x3e) |
| 100| isub | Subtract int | isub | isub = 100 (0x64) |
| 101| iushr | Logical shift right int | iushr | iushr = 124 (0x7c) |
| 102| ixor | Boolean XOR int | ixor | ixor = 130 (0x82) |
| 103| jsr | Jump subroutine | jsrbranchbyte1branchbyte2 | jsr = 168 (0xa8) |
| 104| jsr_w | Jump subroutine (wide index) | jsr_wbranchbyte1branchbyte2branchbyte3branchbyte4 | jsr_w = 201 (0xc9) |
| 105| l2d | Convert long to double | l2d | l2d = 138 (0x8a) |
| 106| l2f | Convert long to float | l2f | l2f = 137 (0x89) |
| 107| l2i | Convert long to int | l2i | l2i = 136 (0x88) |
| 108| ladd | Add long | ladd | ladd = 97 (0x61) |
| 109| laload | Load long from array | laload | laload = 47 (0x2f) |
| 110| land | Boolean AND long | land | land = 127 (0x7f) |
| 111| lastore | Store into long array | lastore | lastore = 80 (0x50) |
| 112| lcmp | Compare long | lcmp | lcmp = 148 (0x94) |
| 113| lconst_<l> | Push long constant | lconst_<l> | lconst_0 = 9 (0x9)lconst_1 = 10 (0xa) |
| 114| ldc | Push item from run-time constant pool | ldcindex | ldc = 18 (0x12) |
| 115| ldc_w | Push item from run-time constant pool (wide index) | ldc_windexbyte1indexbyte2 | ldc_w = 19 (0x13) |
| 116| ldc2_w | Push long or double from run-time constant pool (wide index) | ldc2_windexbyte1indexbyte2 | ldc2_w = 20 (0x14) |
| 117| ldiv | Divide long | ldiv | ldiv = 109 (0x6d) |
| 118| lload | Load long from local variable | lloadindex | lload = 22 (0x16) |
| 119| lload_<n> | Load long from local variable | lload_<n> | lload_0 = 30 (0x1e)lload_1 = 31 (0x1f)lload_2 = 32 (0x20)lload_3 = 33 (0x21) |
| 120| lmul | Multiply long | lmul | lmul = 105 (0x69) |
| 121| lneg | Negate long | lneg | lneg = 117 (0x75) |
| 122| lookupswitch | Access jump table by key match and jump | lookupswitch<0-3 byte pad>defaultbyte1defaultbyte2defaultbyte3defaultbyte4npairs1npairs2npairs3npairs4match-offset pairs... | lookupswitch = 171 (0xab) |
| 123| lor | Boolean OR long | lor | lor = 129 (0x81) |
| 124| lrem | Remainder long | lrem | lrem = 113 (0x71) |
| 125| lreturn | Return long from method | lreturn | lreturn = 173 (0xad) |
| 126| lshl | Shift left long | lshl | lshl = 121 (0x79) |
| 127| lshr | Arithmetic shift right long | lshr | lshr = 123 (0x7b) |
| 128| lstore | Store long into local variable | lstoreindex | lstore = 55 (0x37) |
| 129| lstore_<n> | Store long into local variable | lstore_<n> | lstore_0 = 63 (0x3f)lstore_1 = 64 (0x40)lstore_2 = 65 (0x41)lstore_3 = 66 (0x42) |
| 130| lsub | Subtract long | lsub | lsub = 101 (0x65) |
| 131| lushr | Logical shift right long | lushr | lushr = 125 (0x7d) |
| 132| lxor | Boolean XOR long | lxor | lxor = 131 (0x83) |
| 133| monitorenter | Enter monitor for object | monitorenter | monitorenter = 194 (0xc2) |
| 134| monitorexit | Exit monitor for object | monitorexit | monitorexit = 195 (0xc3) |
| 135| multianewarray | Create new multidimensional array | multianewarrayindexbyte1indexbyte2dimensions | multianewarray = 197 (0xc5) |
| 136| new | Create new object | newindexbyte1indexbyte2 | new = 187 (0xbb) |
| 137| newarray | Create new array | newarrayatype | newarray = 188 (0xbc) |
| 138| nop | Do nothing | nop | nop = 0 (0x0) |
| 139| pop | Pop the top operand stack value | pop | pop = 87 (0x57) |
| 140| pop2 | Pop the top one or two operand stack values | pop2 | pop2 = 88 (0x58) |
| 141| putfield | Set field in object | putfieldindexbyte1indexbyte2 | putfield = 181 (0xb5) |
| 142| putstatic | Set static field in class | putstaticindexbyte1indexbyte2 | putstatic = 179 (0xb3) |
| 143| ret | Return from subroutine | retindex | ret = 169 (0xa9) |
| 144| return | Return void from method | return | return = 177 (0xb1) |
| 145| saload | Load short from array | saload | saload = 53 (0x35) |
| 146| sastore | Store into short array | sastore | sastore = 86 (0x56) |
| 147| sipush | Push short | sipushbyte1byte2 | sipush = 17 (0x11) |
| 148| swap | Swap the top two operand stack values | swap | swap = 95 (0x5f) |
| 149| tableswitch | Access jump table by index and jump | tableswitch<0-3 byte pad>defaultbyte1defaultbyte2defaultbyte3defaultbyte4lowbyte1lowbyte2lowbyte3lowbyte4highbyte1highbyte2highbyte3highbyte4jump offsets... | tableswitch = 170 (0xaa) |
| 150| wide | Extend local variable index by additional bytes |  |wide = 196 (0xc4)|
